<?xml version="1.0" encoding="UTF-8"?>
<persistence version="2.1" xmlns="http://xmlns.jcp.org/xml/ns/persistence" xmlns:xsi="http://www.w3.org/2001/XMLSchema-instance" xsi:schemaLocation="http://xmlns.jcp.org/xml/ns/persistence http://xmlns.jcp.org/xml/ns/persistence/persistence_2_1.xsd">
	<persistence-unit name="JPAExample" transaction-type="RESOURCE_LOCAL">
		<class>jp.co.iccom.suzuki_yoshihiro.jpa_example.entity.BranchEntity</class>
		<class>jp.co.iccom.suzuki_yoshihiro.jpa_example.entity.DepartmentEntity</class>
		<class>jp.co.iccom.suzuki_yoshihiro.jpa_example.entity.UserEntity</class>
		<class>jp.co.iccom.suzuki_yoshihiro.jpa_example.entity.PostEntity</class>
		<class>jp.co.iccom.suzuki_yoshihiro.jpa_example.entity.CommentEntity</class>
		<properties>
			<property name="javax.persistence.jdbc.url" value="jdbc:mysql://localhost/bbs"/>
			<property name="javax.persistence.jdbc.user" value="java"/>
			<property name="javax.persistence.jdbc.password" value="ic-com.Test"/>
			<property name="javax.persistence.jdbc.driver" value="com.mysql.jdbc.Driver"/>
		</properties>
	</persistence-unit>
</persistence>
